docs/Makefile
docs/conf.py
docs/index.rst
docs/make.bat
docs/modules.rst
docs/omero_slurm_client.rst
docs/readme_link.md
docs/requirements.txt
docs/tutorial_link.md
omero_slurm_client/__init__.py
omero_slurm_client/slurm_client.py
resources/__init__.py
resources/convert_job_array.sh
resources/convert_zarr_to_tiff.def
resources/convert_zarr_to_tiff.py
resources/example.config
resources/job_template.sh
resources/pull_images.sh
resources/slurm-config.ini
resources/tutorials/tutorial_GoogleCloud_slurm.md
resources/tutorials/tutorial_cellexpansion.md
resources/tutorials/tutorial_cellprofiler.md
resources/tutorials/tutorial_local_slurm.md
resources/tutorials/images/Cells.tif
resources/tutorials/images/cellexpansion.png
resources/tutorials/images/gc_allow_ssh.PNG
resources/tutorials/images/nuclei_labels.png
resources/tutorials/images/webclient_init_env.PNG
resources/tutorials/images/webclient_init_env_done.PNG
resources/tutorials/images/webclient_run_cellpose.PNG
resources/tutorials/images/webclient_run_workflow.PNG
tests/integration/__init__.py
tests/unit/__init__.py
tests/unit/test_slurm_client.py
omero_slurm_client-1.1.1.dist-info/LICENSE
omero_slurm_client-1.1.1.dist-info/METADATA
omero_slurm_client-1.1.1.dist-info/WHEEL
omero_slurm_client-1.1.1.dist-info/top_level.txt
omero_slurm_client-1.1.1.dist-info/RECORD
