Metadata-Version: 2.1
Name: omero-slurm-client
Version: 1.1.1
Summary: A python library for easy connecting between OMERO (jobs) and a Slurm cluster
Author: Core Facility - Cellular Imaging
Author-email: Torec Luik <t.t.luik@amsterdamumc.nl>, cellularimaging@amsterdamumc.nl
License: Apache License
Project-URL: Homepage, https://github.com/NL-BioImaging/omero-slurm-client
Project-URL: Documentation, https://nl-bioimaging.github.io/omero-slurm-client/
Keywords: omero,slurm,high-performance-computing,fair,image-analysis,bioimaging,high-throughput-screening,high-content-screening,cytomine,biomero,biaflows
Classifier: Programming Language :: Python :: 3
Classifier: Programming Language :: Python :: 3.7
Classifier: Programming Language :: Python :: 3.8
Classifier: Programming Language :: Python :: 3.9
Classifier: Programming Language :: Python :: 3.10
Classifier: License :: OSI Approved :: Apache Software License
Classifier: Operating System :: OS Independent
Requires-Python: >=3.7
License-File: LICENSE
Requires-Dist: requests ==2.31.0
Requires-Dist: requests-cache ==1.1.1
Requires-Dist: fabric ==3.1.0
Requires-Dist: paramiko ==3.2.0
Requires-Dist: importlib-resources >=5.4.0
Provides-Extra: test
Requires-Dist: pytest ; extra == 'test'
Requires-Dist: mock ; extra == 'test'
